SidraSk/SidraELEzz.py
SidraSk/__init__.py
SidraSk-0.0.1.dist-info/LICENSE
SidraSk-0.0.1.dist-info/METADATA
SidraSk-0.0.1.dist-info/WHEEL
SidraSk-0.0.1.dist-info/top_level.txt
SidraSk-0.0.1.dist-info/RECORD
