Metadata-Version: 2.1
Name: SidraSk
Version: 0.0.1
Summary: tools Checker Sk
Home-page: https://github.com/SidraELEzz/SidraSk
Author: SidraELEzz
Author-email: 
License: UNKNOWN
Project-URL: Bug Tracker, https://github.com/pypa/sampleproject/issues
Keywords: Checker-Sk
Platform: UNKNOWN
Classifier: Development Status :: 1 - Planning
Classifier: Intended Audience :: Developers
Classifier: Programming Language :: Python :: 3
Classifier: Operating System :: Unix
Classifier: Operating System :: MacOS :: MacOS X
Classifier: Operating System :: Microsoft :: Windows
License-File: LICENSE
Requires-Dist: requests
